trfedit/CrosstablePage.py
trfedit/GamesDialog.py
trfedit/MenuBar.py
trfedit/PlayerBackend.py
trfedit/RoundDatesBackend.py
trfedit/TournamentPage.py
trfedit/TreeView.py
trfedit/TreeViewPage.py
trfedit/Window.py
trfedit/XXFieldsBackend.py
trfedit/__init__.py
trfedit/__main__.py
trfedit/resources/__init__.py
trfedit/resources/trfedit.png
trfedit-1.1.0.data/data/share/applications/trfedit.desktop
trfedit-1.1.0.data/data/share/icons/hicolor/256x256/apps/trfedit.png
trfedit-1.1.0.dist-info/LICENSE
trfedit-1.1.0.dist-info/METADATA
trfedit-1.1.0.dist-info/WHEEL
trfedit-1.1.0.dist-info/entry_points.txt
trfedit-1.1.0.dist-info/top_level.txt
trfedit-1.1.0.dist-info/RECORD
