Metadata-Version: 2.1
Name: trfedit
Version: 1.1.0
Summary: A GUI editor for the fide approved tournament report format: trf
Home-page: https://github.com/sklangen/trfedit
Author: Schachklub Langen e. V.
Author-email: Turnierleiter@sklangen.de
License: GPLv3+
Keywords: trf,fide,chess,tournaments
Platform: UNKNOWN
Classifier: Development Status :: 5 - Production/Stable
Classifier: Intended Audience :: End Users/Desktop
Classifier: License :: OSI Approved :: GNU General Public License v3 or later (GPLv3+)
Classifier: Operating System :: OS Independent
Classifier: Programming Language :: Python :: 3.8
Classifier: Topic :: Utilities
License-File: LICENSE
Requires-Dist: trf
